<?xml version="1.0" encoding="iso-8859-1"?>
<!-- This XML representation of an RCO structure was generated by Rcomage v1.1.2 -->
<RcoFile UMDFlag="0" rcomageXmlVer="1.1" type="ps3" minFirmwareVer="unknownId0x130">
	<MainTree name="xai_plugin">
		<ImageTree>
			<Image name="tex_check2_ws" src="Images\tex_check2_ws.gim" format="gim" compression="zlib" unknownByte="0" />
			<Image name="tex_error_ws" src="Images\tex_error_ws.gim" format="gim" compression="zlib" unknownByte="0" />
			<Image name="tex_notification_info" src="Images\tex_notification_info.gim" format="gim" compression="zlib" unknownByte="0" />
			<Image name="tex_notification_info2" src="Images\tex_notification_info2.gim" format="gim" compression="zlib" unknownByte="0" />
			<Image name="tex_warning" src="Images\tex_warning.gim" format="gim" compression="zlib" unknownByte="0" />
		</ImageTree>
		<TextTree>
			<TextLang src="Text\00_Japanese.xml" language="00_Japanese" format="utf16" />
			<TextLang src="Text\01_English_US.xml" language="01_English_US" format="utf16" />
			<TextLang src="Text\02_French.xml" language="02_French" format="utf16" />
			<TextLang src="Text\03_Spanish.xml" language="03_Spanish" format="utf16" />
			<TextLang src="Text\04_German.xml" language="04_German" format="utf16" />
			<TextLang src="Text\05_Italian.xml" language="05_Italian" format="utf16" />
			<TextLang src="Text\06_Dutch.xml" language="06_Dutch" format="utf16" />
			<TextLang src="Text\07_Portuguese_PT.xml" language="07_Portuguese_PT" format="utf16" />
			<TextLang src="Text\08_Russian.xml" language="08_Russian" format="utf16" />
			<TextLang src="Text\09_Korean.xml" language="09_Korean" format="utf16" />
			<TextLang src="Text\10_Chinese_T.xml" language="10_Chinese_T" format="utf16" />
			<TextLang src="Text\11_Chinese_S.xml" language="11_Chinese_S" format="utf16" />
			<TextLang src="Text\12_Finnish.xml" language="12_Finnish" format="utf16" />
			<TextLang src="Text\13_Swedish.xml" language="13_Swedish" format="utf16" />
			<TextLang src="Text\14_Danish.xml" language="14_Danish" format="utf16" />
			<TextLang src="Text\15_Norwegian.xml" language="15_Norwegian" format="utf16" />
			<TextLang src="Text\16_Polish.xml" language="16_Polish" format="utf16" />
			<TextLang src="Text\17_Portuguese_BR.xml" language="17_Portuguese_BR" format="utf16" />
			<TextLang src="Text\18_English_GB.xml" language="18_English_GB" format="utf16" />
			<TextLang src="Text\19_Turkish.xml" language="19_Turkish" format="utf16" />
		</TextTree>
		<ObjectTree>
			<Page name="Xai" pageMode="0x1101" pageOnInit="nothing" pageOnCancel="nothing" pageOnContext="nothing" pageOnActivate="nothing"></Page>
			<Page name="Tool" pageMode="0x1101" pageOnInit="nothing" pageOnCancel="nothing" pageOnContext="nothing" pageOnActivate="nothing"></Page>
			<Page name="Mouse" pageMode="0x1101" pageOnInit="nothing" pageOnCancel="nothing" pageOnContext="nothing" pageOnActivate="nothing"></Page>
		</ObjectTree>
	</MainTree>
</RcoFile>
